{
	"configurations" : 
	[
		{
			"directories" : 
			[
				{
					"build" : ".",
					"hasInstallRule" : true,
					"jsonFile" : "directory-.-Debug-b296b254b568b6a75137.json",
					"minimumCMakeVersion" : 
					{
						"string" : "3.12"
					},
					"projectIndex" : 0,
					"source" : ".",
					"targetIndexes" : 
					[
						0,
						1
					]
				}
			],
			"name" : "Debug",
			"projects" : 
			[
				{
					"directoryIndexes" : 
					[
						0
					],
					"name" : "imu_calib",
					"targetIndexes" : 
					[
						0,
						1
					]
				}
			],
			"targets" : 
			[
				{
					"directoryIndex" : 0,
					"id" : "imu_calib_uninstall::@6890427a1f51a3e7e1df",
					"jsonFile" : "target-imu_calib_uninstall-Debug-4e874269a086ede4d482.json",
					"name" : "imu_calib_uninstall",
					"projectIndex" : 0
				},
				{
					"directoryIndex" : 0,
					"id" : "uninstall::@6890427a1f51a3e7e1df",
					"jsonFile" : "target-uninstall-Debug-f55bc4e037398334a6fe.json",
					"name" : "uninstall",
					"projectIndex" : 0
				}
			]
		}
	],
	"kind" : "codemodel",
	"paths" : 
	{
		"build" : "/home/lolade/Robotics/ros2_ws/src/imu_calib/build",
		"source" : "/home/lolade/Robotics/ros2_ws/src/imu_calib"
	},
	"version" : 
	{
		"major" : 2,
		"minor" : 3
	}
}
